{"list":[{"id":0,"kana":"一","arti":"satu","romanji":"ichi","contoh":[{"kana":"一人","romanji":"hitori","arti":"sendiri/satu orang"},{"kana":"一つ","romanji":"hitotsu","arti":"satu benda"},{"kana":"一緒","romanji":"issho","arti":"bersama/together"},{"kana":"一杯","romanji":"ippai","arti":"satu cangkir"},{"kana":"一回","romanji":"ikkai","arti":"satu kali"}]},{"id":1,"kana":"二","arti":"dua","romanji":"ni","contoh":[{"kana":"二人","romanji":"futari","arti":"berdua/dua orang"},{"kana":"二つ","romanji":"futatsu","arti":"dua benda"}]},{"id":2,"kana":"三","arti":"tiga","romanji":"san","contoh":[{"kana":"三人","romanji":"sannin","arti":"bertiga/tiga orang"}]},{"id":3,"kana":"四","arti":"empat","romanji":"shi/yon"},{"id":4,"kana":"五","arti":"lima","romanji":"go"},{"id":5,"kana":"六","arti":"enam","romanji":"roku"},{"id":6,"kana":"七","arti":"tujuh","romanji":"shichi/nana"},{"id":7,"kana":"八","arti":"delapan","romanji":"hachi"},{"id":8,"kana":"九","arti":"sembilan","romanji":"kyuu/ku"},{"id":9,"kana":"十","arti":"sepuluh","romanji":"juu/ji"},{"id":10,"kana":"百","arti":"seratus/100","romanji":"hyaku"},{"id":11,"kana":"千","arti":"seribu/1000","romanji":"sen"},{"id":12,"kana":"万","arti":"sepuluh ribu/10000","romanji":"man"},{"id":13,"kana":"円","arti":"yen","romanji":"en"},{"id":14,"kana":"口","arti":"mulut","romanji":"kuchi","contoh":[{"kana":"入口","arti":"pintu masuk","romanji":"iriguchi"},{"kana":"出口","arti":"pintu keluar","romanji":"deguchi"}]},{"id":15,"kana":"目","arti":"mata","romanji":"me","contoh":[{"romanji":"mokuteki","arti":"tujuan/maksud","kana":"目的"},{"romanji":"medatsu","arti":"terlihat/menonjol","kana":"目立つ"},{"romanji":"mokuji","arti":"daftar isi/indeks","kana":"目次"}]},{"id":16,"kana":"耳","arti":"telinga","romanji":"mimi"},{"id":17,"kana":"手","arti":"tangan","romanji":"te","contoh":[{"kana":"手紙","arti":"surat","romanji":"tegami"},{"kana":"手洗い","arti":"tempat cuci tangan/wastafel","romanji":"tearai"}]},{"id":18,"kana":"足","arti":"kaki","romanji":"ashi"},{"id":19,"kana":"本","arti":"buku","romanji":"hon","contoh":[{"kana":"本当","arti":"benar/kebenaran","romanji":"hontou"},{"kana":"本屋","arti":"toko buku","romanji":"honya"},{"kana":"本気","arti":"serius/sungguh-sungguh","romanji":"honki"},{"kana":"本物","arti":"asli/barang asli","romanji":"honmono"}]},{"id":20,"kana":"人","arti":"orang","romanji":"hito","contoh":[{"romanji":"ningen","arti":"manusia","kana":"人間"},{"romanji":"jinsei","arti":"kehidupan manusia","kana":"人生"},{"romanji":"otona","arti":"orang dewasa","kana":"大人"},{"romanji":"jinkou","arti":"populasi","kana":"人口"}]},{"id":21,"kana":"名","arti":"nama","romanji":"na"},{"id":22,"kana":"学","arti":"belajar","romanji":"gaku","contoh":[{"kana":"学校","arti":"sekolah","romanji":"gakkou"},{"kana":"学生","romanji":"gakusei","arti":"siswa"},{"kana":"大学","romanji":"daigaku","arti":"kampus/universitas"},{"kana":"学ぶ","romanji":"manabu","arti":"belajar"}]},{"id":23,"kana":"子","arti":"anak","romanji":"ko","contoh":[{"romanji":"kodomo","arti":"anak-anak","kana":"子供"},{"romanji":"onnanoko","arti":"anak perempuan","kana":"女の子"},{"romanji":"otokonoko","arti":"anak laki-laki","kana":"男の子"},{"romanji":"shison","arti":"generasi muda","kana":"子孫"}]},{"id":24,"kana":"男","arti":"laki-laki/cowok","romanji":"otoko","contoh":[{"romanji":"dansei","arti":"pria","kana":"男性"},{"romanji":"otoko no ko","arti":"anak laki-laki","kana":"男の子"}]},{"id":25,"kana":"女","arti":"perempuan/cewek","romanji":"onna","contoh":[{"romanji":"josei","arti":"wanita","kana":"女性"},{"romanji":"onna no ko","arti":"anak perempuan","kana":"女の子"}]},{"id":26,"kana":"田","arti":"ladang","romanji":"ta"},{"id":27,"kana":"山","arti":"gunung","romanji":"yama","contoh":[{"romanji":"fujisan","arti":"gunung fuji","kana":"富士山"},{"romanji":"sanchou","arti":"puncak gunung","kana":"山頂"},{"romanji":"kazan","arti":"gunung api","kana":"火山"},{"romanji":"sanmyaku","arti":"pegunungan","kana":"山脈"}]},{"id":28,"kana":"川","arti":"sungai","romanji":"kawa","contoh":[{"romanji":"kawashita","arti":"hilir","kana":"川下"},{"romanji":"kawakami","arti":"hulu","kana":"川上"}]},{"id":29,"kana":"雨","arti":"hujan","romanji":"ame"},{"id":30,"kana":"花","arti":"bunga","romanji":"hana","contoh":[{"romanji":"hanazono","arti":"taman bunga","kana":"花園"},{"romanji":"nobana","arti":"bunga liar","kana":"野花"},{"romanji":"kabin","arti":"vas bunga","kana":"花瓶"},{"romanji":"hanabi","arti":"kembang api","kana":"花火"}]},{"id":31,"kana":"木","arti":"pohon","romanji":"ki","contoh":[{"romanji":"mokuzai","arti":"kayu","kana":"木材"},{"romanji":"mokuyoubi","arti":"kamis","kana":"木曜日"},{"romanji":"mokkou","arti":"kerajinan kayu","kana":"木工"}]},{"id":32,"kana":"火","arti":"api","romanji":"hi","contoh":[{"romanji":"kaji","arti":"kebakaran.","kana":"火事"},{"romanji":"kayoubi","arti":"selasa","kana":"火曜日"},{"romanji":"kazan","arti":"gunung berapi","kana":"火山"},{"romanji":"hanabi","arti":"kembang api","kana":"花火"}]},{"id":33,"kana":"水","arti":"air","romanji":"mizu","contoh":[{"romanji":"suidou","arti":"saluran air","kana":"水道"},{"romanji":"suiteki","arti":"tetesan air","kana":"水滴"},{"romanji":"suiyoubi","arti":"selasa","kana":"水曜日"}]},{"id":34,"kana":"土","arti":"tanah","romanji":"tsuchi"},{"id":35,"kana":"金","arti":"emas/uang","romanji":"kin","contoh":[{"kana":"お金","arti":"uang","romanji":"okane"},{"kana":"金銭","arti":"keuangan","romanji":"kinsen"},{"kana":"金曜日","arti":"jumat","romanji":"kinyoubi"}]},{"id":36,"kana":"銀","arti":"perak","romanji":"gin"},{"id":37,"kana":"車","arti":"mobil","romanji":"kuruma"},{"id":38,"kana":"自","arti":"sendiri","romanji":"ji"},{"id":39,"kana":"友","arti":"teman","romanji":"tomo"},{"id":40,"kana":"行","arti":"pergi","romanji":"iku"},{"id":41,"kana":"来","arti":"datang","romanji":"kuru"},{"id":42,"kana":"見","arti":"lihat","romanji":"miru"},{"id":43,"kana":"食","arti":"makan/makan","romanji":"taberu"},{"id":44,"kana":"飲","arti":"minum/drink","romanji":"nomu"},{"id":45,"kana":"読","arti":"membaca/read","romanji":"yomu"},{"id":46,"kana":"書","arti":"menulis/write/tulis","romanji":"kaku"},{"id":47,"kana":"話","arti":"cerita/bicara/talk/speech","romanji":"hanashu"},{"id":48,"kana":"入","arti":"masuk","romanji":"hairu"},{"id":49,"kana":"出","arti":"keluar","romanji":"deru"},{"id":50,"kana":"開","arti":"buka","romanji":"akeru"},{"id":51,"kana":"閉","arti":"tutup","romanji":"tojiru"},{"id":52,"kana":"電","arti":"listrik","romanji":"den","contoh":[{"kana":"電車","romanji":"densha","arti":"mobil"},{"kana":"電話","romanji":"denwa","arti":"telepon"},{"kana":"電気","romanji":"denki","arti":"listrik"}]},{"id":53,"kana":"日","arti":"hari/matahari","romanji":"nichi","contoh":[{"kana":"日曜日","romanji":"nichiyoubi","arti":"minggu"},{"kana":"今日","romanji":"kyou","arti":"hari ini/today"},{"kana":"明日","romanji":"ashita","arti":"besok"}]},{"id":54,"kana":"国","arti":"negara","romanji":"koku"},{"id":55,"kana":"年","arti":"tahun","romanji":"nen"},{"id":56,"kana":"月","arti":"bulan","romanji":"gatsu/tsuki"},{"id":57,"kana":"好","arti":"suka","romanji":"suki"},{"id":58,"kana":"中","arti":"tengah","romanji":"naka"},{"id":59,"kana":"大","arti":"besar","romanji":"ooki"},{"id":60,"kana":"小","arti":"kecil","romanji":"chiisai"},{"id":61,"kana":"低","arti":"rendah","romanji":"dai"},{"id":62,"kana":"時","arti":"waktu/jam","romanji":"jitsu"},{"id":63,"kana":"分","arti":"menit","romanji":"futatsu/bun"},{"id":64,"kana":"秒","arti":"detik","romanji":"seikatsu"},{"id":65,"kana":"長","arti":"panjang","romanji":"naga"},{"id":66,"kana":"近","arti":"dekat","romanji":"chika"},{"id":67,"kana":"遠","arti":"jauh","romanji":"tooi"},{"id":68,"arti":"sedikit","romanji":"sukoshi","kana":"少"},{"id":69,"kana":"多","arti":"banyak","romanji":"ooi"},{"id":70,"kana":"広","arti":"luas","romanji":"hiro"},{"id":71,"kana":"左","arti":"kiri","romanji":"hidari"},{"id":72,"kana":"右","arti":"kanan","romanji":"migi"},{"id":73,"kana":"前","arti":"depan","romanji":"mae"},{"id":74,"kana":"後","arti":"belakang/after/later/nanti","romanji":"ushiro"},{"id":75,"kana":"上","arti":"atas","romanji":"ue"},{"id":76,"kana":"下","arti":"bawah","romanji":"shita"},{"id":77,"kana":"今","arti":"sekarang","romanji":"ima"},{"id":78,"kana":"週","arti":"minggu/week","romanji":"shuu"},{"id":79,"kana":"回","arti":"kali/putaran/round/banyaknya/counter","romanji":"kai"},{"id":80,"kana":"外","arti":"luar","romanji":"soto"},{"id":81,"kana":"気","arti":"udara","romanji":"ki"},{"id":82,"kana":"門","arti":"gerbang","romanji":"mon"},{"id":83,"kana":"家","arti":"rumah","romanji":"ie"},{"id":84,"kana":"間","arti":"jarak/ruang/diantara/space/gap/between/interval/stretch/distance","romanji":"aida"},{"id":85,"kana":"弟","arti":"adik laki/adik cowok","romanji":"otouto"},{"id":86,"kana":"妹","arti":"adik perempuan/adik cewek","romanji":"imouto"},{"id":87,"kana":"父","arti":"ayah","romanji":"chichi"},{"id":88,"kana":"母","arti":"ibu","romanji":"haha"},{"id":89,"kana":"兄","arti":"kakak laki","romanji":"ani"},{"id":90,"kana":"姉","arti":"kakak perempuan","romanji":"ane"},{"id":91,"kana":"半","arti":"setengah","romanji":"han"},{"id":92,"kana":"語","arti":"bahasa","romanji":"go"},{"id":93,"kana":"校","arti":"sekolah","romanji":"kou"},{"id":94,"kana":"聞","arti":"dengar","romanji":"kiku"},{"id":95,"kana":"覚","arti":"ingat","romanji":"oboe"},{"id":96,"kana":"忘","arti":"lupa","romanji":"wasure"},{"id":97,"kana":"寝","arti":"tidur","romanji":"neru"},{"id":98,"kana":"何","arti":"apa","romanji":"nani"},{"id":99,"kana":"私","arti":"saya","romanji":"watashi"},{"id":100,"kana":"君","arti":"kamu","romanji":"kimi"},{"id":101,"kana":"毎","arti":"setiap","romanji":"mai"},{"id":102,"kana":"休","arti":"libur/istirahat","romanji":"yasu"},{"id":103,"kana":"北","arti":"utara","romanji":"kita"},{"id":104,"kana":"南","arti":"selatan","romanji":"minami"},{"id":105,"kana":"西","arti":"barat","romanji":"nishi"},{"id":106,"kana":"東","arti":"timur","romanji":"higashi"},{"id":107,"kana":"犬","arti":"anjing","romanji":"inu"},{"id":108,"kana":"猫","arti":"kucing","romanji":"neko"},{"id":109,"kana":"鳥","arti":"burung","romanji":"tori"},{"id":110,"kana":"魚","arti":"ikan","romanji":"sakana"},{"id":111,"kana":"亀","arti":"kura-kura","romanji":"kame"},{"id":112,"kana":"蛇","arti":"ular","romanji":"hebi"},{"id":113,"kana":"馬","arti":"kuda","romanji":"uma"},{"id":114,"kana":"象","arti":"gajah","romanji":"zou"},{"id":115,"kana":"虎","arti":"harimau","romanji":"tora"},{"id":116,"kana":"羊","arti":"domba","romanji":"hitsuji"},{"id":117,"kana":"猿","arti":"monyet","romanji":"saru"},{"id":118,"kana":"狐","arti":"rubah","romanji":"kitsune"},{"id":119,"kana":"牛","arti":"sapi","romanji":"ushi"},{"id":120,"kana":"豚","arti":"babi","romanji":"buta"},{"id":121,"kana":"高","arti":"mahal/tinggi","romanji":"takai"},{"id":122,"kana":"安","arti":"murah","romanji":"yasui"},{"id":123,"kana":"新","arti":"baru","romanji":"atarashii"},{"id":124,"kana":"古","arti":"lama/tua","romanji":"furui"},{"id":125,"kana":"強","arti":"kuat","romanji":"tsuyoi"},{"id":126,"kana":"弱","arti":"lemah","romanji":"yowai"},{"id":127,"kana":"速","arti":"cepat","romanji":"hayai"},{"id":128,"kana":"遅","arti":"lambat","romanji":"osoi"},{"id":129,"kana":"春","arti":"musim semi","romanji":"haru"},{"id":130,"kana":"夏","arti":"musim panas","romanji":"natsu"},{"id":131,"kana":"秋","arti":"musim gugur","romanji":"aki"},{"id":132,"kana":"冬","arti":"musim dingin","romanji":"fuyu"},{"id":133,"kana":"赤","arti":"merah","romanji":"aka"},{"id":134,"kana":"青","arti":"biru","romanji":"ao"},{"id":135,"kana":"緑","arti":"hijau","romanji":"midori"},{"id":136,"kana":"黒","arti":"hitam","romanji":"kuro"},{"id":137,"kana":"白","arti":"putih","romanji":"shiro"},{"id":138,"kana":"暑","arti":"panas","romanji":"atsui"},{"id":139,"kana":"寒","arti":"dingin","romanji":"samui"},{"id":140,"kana":"頭","arti":"kepala","romanji":"atama"},{"id":141,"kana":"髪","arti":"rambut","romanji":"kami"},{"id":142,"kana":"力","arti":"kekuatan/ability/strength/power","romanji":"chikara"},{"id":143,"kana":"刀","arti":"pedang","romanji":"katana"},{"id":144,"kana":"明","arti":"terang/ceria/cerah","romanji":"akarui"},{"id":145,"kana":"言","arti":"kata","romanji":"koto"},{"kana":"体","id":146,"arti":"tubuh/badan","romanji":"karada"},{"kana":"太","id":147,"arti":"gendut","romanji":"futoi"},{"kana":"彼","id":148,"arti":"dia","romanji":"kare"},{"kana":"海","id":149,"arti":"laut/pantai","romanji":"umi"},{"kana":"住","id":150,"arti":"menginap/tinggal/pindah/menempati","romanji":"shu"},{"kana":"始","id":151,"arti":"awal/mulai/start/pertama/begin","romanji":"haji"},{"kana":"起","id":152,"arti":"bangun","romanji":"okiru"},{"kana":"先","id":153,"arti":"depan/sebelum/pertama/ujung","romanji":"saki"},{"kana":"生","id":154,"arti":"lahir/hidup/tumbuh/live","romanji":"saki"},{"kana":"林","id":155,"arti":"wood/pohon/hutan","romanji":"hayashi"},{"kana":"森","id":156,"arti":"hutan","romanji":"mori"},{"kana":"米","id":157,"arti":"beras/nasi","romanji":"kome"},{"kana":"肉","id":158,"arti":"daging","romanji":"niku"},{"kana":"茶","id":159,"arti":"teh","romanji":"ocha"},{"kana":"物","id":160,"arti":"objek/benda/thing","romanji":"mono"},{"kana":"方","id":161,"arti":"arah/direction","romanji":"hou"},{"kana":"町","id":162,"arti":"kota/town","romanji":"machi"},{"kana":"寺","id":163,"arti":"kuil/temple/candi","romanji":"tera"},{"kana":"朝","id":164,"arti":"pagi","romanji":"asa"},{"kana":"店","id":165,"arti":"toko","romanji":"mise"},{"kana":"買","id":166,"arti":"beli","romanji":"kairu"},{"kana":"図","id":167,"arti":"gambar/peta/grafik/map","romanji":"zu"},{"kana":"駅","id":168,"arti":"stasiun","romanji":"eki"},{"kana":"傘","id":169,"arti":"payung","romanji":"kasa"},{"kana":"暗","id":170,"arti":"gelap/dark","romanji":"kurai"},{"kana":"元","id":171,"arti":"asal/dasar/mula/murni/sehat","romanji":"gen"},{"kana":"立","id":172,"arti":"stand/berdiri","romanji":"tatsu"},{"kana":"帰","id":173,"arti":"pulang/go home/kembali/return","romanji":"kaeru"},{"kana":"天","id":174,"arti":"langit/surga","romanji":"ten"},{"kana":"石","id":175,"arti":"batu/rock/stone","romanji":"ishi"},{"kana":"卵","arti":"telur/telor","romanji":"tamago","id":176},{"kana":"暇","arti":"free/bebas","romanji":"hima","id":177},{"kana":"作","arti":"buat/bikin/make","romanji":"tsukuru","id":178},{"kana":"服","arti":"pakaian","romanji":"fuku","id":179},{"kana":"空","arti":"sky/free","romanji":"kuu/sora","id":180},{"kana":"午","arti":"go/sore","romanji":"go","id":181},{"kana":"社","arti":"kantor/company/komunitas","romanji":"sha","id":182},{"kana":"会","arti":"meet/bertemu/rindu/kumpul","romanji":"kai","id":183},{"kana":"早","arti":"early/fast/quick","romanji":"sou","id":184},{"kana":"道","arti":"path/way/street/jalan","romanji":"michi","id":185},{"kana":"洗","arti":"wash/cuci","romanji":"sen/arau","id":186},{"kana":"事","romanji":"ji/goto","arti":"hal/urusan/pekerjaan/perkara/kejadian","id":187},{"kana":"場","romanji":"ba","arti":"tempat/lapangan/arena/lingkungan","id":188},{"kana":"事","romanji":"ji/koto","arti":"hal/urusan/pekerjaan/perkara/kejadian","id":189},{"kana":"場","romanji":"ba","arti":"tempat/lapangan/arena/lingkungan","id":190},{"kana":"発","romanji":"hatsu","arti":"berangkat/pengiriman/penemuan/keluar","id":191},{"kana":"者","romanji":"sha/mono","arti":"orang/pelaku/individu","id":192},{"kana":"問","romanji":"mon/to","arti":"pertanyaan/permintaan/mencari tahu","id":193},{"kana":"主","romanji":"shu/nushi","arti":"pemilik/tuan/kepala/tuan rumah","id":194},{"kana":"不","romanji":"fu/bu","arti":"tidak/negatif","id":195},{"kana":"公","romanji":"kou","arti":"publik/umum/pemerintah","id":196},{"kana":"持","romanji":"ji/mo","arti":"memegang/memiliki","id":197},{"kana":"思","romanji":"shi/omou","arti":"berpikir/merasa","id":198},{"kana":"正","romanji":"sei/shou","arti":"benar/tepat/lurus/kebijakan","id":199},{"kana":"心","romanji":"shin/kokoro","arti":"hati/pikiran/perasaan","id":200},{"kana":"世","romanji":"sei/yo","arti":"dunia/generasi/zaman","id":201},{"kana":"京","romanji":"kyou","arti":"ibu kota","id":202},{"kana":"員","romanji":"in","arti":"anggota/staf/personel","id":203},{"kana":"同","romanji":"dou/onaji","arti":"sama/serupa/bersama","id":204},{"kana":"文","romanji":"bun/mon","arti":"tulisan/bahasa/budaya","id":205},{"kana":"重","romanji":"juu/omoi","arti":"berat/penting/ganda","id":206},{"kana":"品","romanji":"hin/shina","arti":"barang/produk/kualitas","id":207},{"kana":"工","romanji":"kou","arti":"teknik/pabrik/industri","id":208},{"kana":"止","romanji":"shi/to","arti":"berhenti/henti/stop","id":209},{"kana":"待","romanji":"tai/machi","arti":"menunggu/menanti/tunggu","id":210},{"kana":"死","romanji":"shi","arti":"kematian/mati","id":211},{"kana":"計","romanji":"kei/hakaru","arti":"menghitung/perencanaan/rencana","id":212},{"kana":"画","romanji":"ga","arti":"gambar/lukisan","id":213},{"kana":"建","romanji":"ken/tateru","arti":"membangun/konstruksi","id":214},{"kana":"息","romanji":"musuko","arti":"anak laki","id":215},{"kana":"娘","romanji":"musume","arti":"anak perempuan","id":216},{"kana":"夫","romanji":"otto","arti":"suami","id":217},{"kana":"妻","romanji":"tsuma","arti":"istri","id":218},{"kana":"関","romanji":"seki","arti":"hubungan/gerbang/barrier","id":219},{"kana":"⻌","romanji":"shinnyo","arti":"jalan/path/gerakan/move","id":220},{"kana":"運","romanji":"un","arti":"tadir/perjalanan","id":221},{"kana":"位","romanji":"i","arti":"kedudukan/posisi/peringkat","id":222}]}